sklite/__init__.py
sklite/__version__.py
sklite/all_.py
sklite/lazy_.py
sklite/lib/__init__.py
sklite/lib/abstract.py
sklite/lib/exceptions.py
sklite/lib/models/__init__.py
sklite/lib/models/base.py
sklite/lib/models/ensemble.py
sklite/lib/models/naive_bayes.py
sklite/lib/models/neighbors.py
sklite/lib/models/neural_network.py
sklite/lib/models/svc.py
sklite/lib/models/tree.py
sklite-0.0.2.dist-info/LICENSE.txt
sklite-0.0.2.dist-info/METADATA
sklite-0.0.2.dist-info/RECORD
sklite-0.0.2.dist-info/WHEEL
sklite-0.0.2.dist-info/top_level.txt
