Metadata-Version: 2.1
Name: sklite
Version: 0.0.2
Summary: Use Scikit Learn models in Flutter
Home-page: https://github.com/axegon/sklite
Author: Alexander Ejbekov
Author-email: alexander@kialo.ai
License: MIT
Platform: UNKNOWN
Classifier: Development Status :: 4 - Beta
Classifier: Intended Audience :: Developers
Classifier: Natural Language :: English
Classifier: License :: OSI Approved :: MIT License
Classifier: Programming Language :: Python
Classifier: Programming Language :: Python :: 3.6
Classifier: Programming Language :: Python :: 3.7
Classifier: Programming Language :: Python :: 3.8
